tests/__init__.py
tests/test_client.py
wordpress_api_client/__init__.py
wordpress_api_client/client.py
wordpress_api_client/exceptions.py
wordpress_api_client/logger.py
wordpress_api_client-0.1.3.dist-info/LICENSE
wordpress_api_client-0.1.3.dist-info/METADATA
wordpress_api_client-0.1.3.dist-info/WHEEL
wordpress_api_client-0.1.3.dist-info/top_level.txt
wordpress_api_client-0.1.3.dist-info/RECORD
