Metadata-Version: 2.2
Name: wordpress_api_client
Version: 0.1.3
Summary: A Python client for interacting with the WordPress REST API.
Home-page: https://github.com/nnevdokimov/wordpress_api_client
Author: nnevdokimov
Author-email: nick.evdokimovv@gmail.com
Classifier: Programming Language :: Python :: 3
Classifier: License :: OSI Approved :: MIT License
Classifier: Operating System :: OS Independent
Requires-Python: >=3.7
License-File: LICENSE
Requires-Dist: requests
Dynamic: author
Dynamic: author-email
Dynamic: classifier
Dynamic: description
Dynamic: description-content-type
Dynamic: home-page
Dynamic: requires-dist
Dynamic: requires-python
Dynamic: summary
